{
    "label": "\u001b[D\u001b[C\u001b[A\u001b[B",
    "timestamp": 1771529273.647902,
    "screen_width": 1400,
    "screen_height": 900,
    "points": [
        {
            "target_x": 70,
            "target_y": 45,
            "gaze_h": 0.44005808514574873,
            "gaze_v": 0.40630196847504296,
            "std_h": 0.02011843872892362,
            "std_v": 0.005241976241497544,
            "samples": 103,
            "samples_total": 103,
            "samples_blink": 0
        },
        {
            "target_x": 700,
            "target_y": 45,
            "gaze_h": 0.6115539952164177,
            "gaze_v": 0.39958147029249075,
            "std_h": 0.01383780136060269,
            "std_v": 0.006079718199141551,
            "samples": 98,
            "samples_total": 101,
            "samples_blink": 3
        },
        {
            "target_x": 1330,
            "target_y": 45,
            "gaze_h": 0.788588189558801,
            "gaze_v": 0.3862475128857388,
            "std_h": 0.020006471060845805,
            "std_v": 0.006855083547651249,
            "samples": 91,
            "samples_total": 96,
            "samples_blink": 5
        },
        {
            "target_x": 350,
            "target_y": 45,
            "gaze_h": 0.5395979207810186,
            "gaze_v": 0.3972919188580994,
            "std_h": 0.02102370082238018,
            "std_v": 0.006258543617259712,
            "samples": 101,
            "samples_total": 105,
            "samples_blink": 4
        },
        {
            "target_x": 1050,
            "target_y": 45,
            "gaze_h": 0.7295658487180647,
            "gaze_v": 0.3992841730391897,
            "std_h": 0.018368890520728307,
            "std_v": 0.005928154773559444,
            "samples": 101,
            "samples_total": 104,
            "samples_blink": 3
        },
        {
            "target_x": 350,
            "target_y": 225,
            "gaze_h": 0.5379186822122324,
            "gaze_v": 0.4142120685206612,
            "std_h": 0.023651801327208895,
            "std_v": 0.006117606274374843,
            "samples": 100,
            "samples_total": 105,
            "samples_blink": 5
        },
        {
            "target_x": 1050,
            "target_y": 225,
            "gaze_h": 0.7054226086110891,
            "gaze_v": 0.4013509583354871,
            "std_h": 0.023672120717405248,
            "std_v": 0.006978501527497519,
            "samples": 99,
            "samples_total": 105,
            "samples_blink": 6
        },
        {
            "target_x": 70,
            "target_y": 450,
            "gaze_h": 0.47206461796600263,
            "gaze_v": 0.41436065677363054,
            "std_h": 0.02724263549643525,
            "std_v": 0.007146053529448735,
            "samples": 100,
            "samples_total": 104,
            "samples_blink": 4
        },
        {
            "target_x": 700,
            "target_y": 450,
            "gaze_h": 0.6481384837623292,
            "gaze_v": 0.4150392293791296,
            "std_h": 0.020308802357013697,
            "std_v": 0.00879804223395917,
            "samples": 99,
            "samples_total": 106,
            "samples_blink": 7
        },
        {
            "target_x": 1330,
            "target_y": 450,
            "gaze_h": 0.7755047066754897,
            "gaze_v": 0.4133361985499011,
            "std_h": 0.04908451180680242,
            "std_v": 0.0065839248172441245,
            "samples": 100,
            "samples_total": 106,
            "samples_blink": 6
        },
        {
            "target_x": 70,
            "target_y": 855,
            "gaze_h": 0.4627831808549874,
            "gaze_v": 0.43067923620751347,
            "std_h": 0.04314519634019095,
            "std_v": 0.0075847234171433865,
            "samples": 94,
            "samples_total": 106,
            "samples_blink": 12
        },
        {
            "target_x": 700,
            "target_y": 855,
            "gaze_h": 0.6129516758830227,
            "gaze_v": 0.4247953372001172,
            "std_h": 0.017021312715570863,
            "std_v": 0.006933205603957545,
            "samples": 100,
            "samples_total": 106,
            "samples_blink": 6
        },
        {
            "target_x": 1330,
            "target_y": 855,
            "gaze_h": 0.7645727885685061,
            "gaze_v": 0.43692736508885976,
            "std_h": 0.023621337424638473,
            "std_v": 0.004737015005127426,
            "samples": 100,
            "samples_total": 104,
            "samples_blink": 4
        }
    ],
    "model": {
        "x_slope": 3906.5213217166047,
        "x_intercept": -1730.673862148263,
        "y_slope": 21007.50941417555,
        "y_intercept": -8275.205060965409,
        "type": "poly2",
        "x_coef": [
            11062.093564090717,
            -3833.1024280038664,
            -50547.11133844276,
            14251.405626471642,
            1490.1918713840591,
            50613.76878224253
        ],
        "y_coef": [
            -207.1203214087133,
            20703.544296038246,
            -52725.98556367927,
            -42360.40035635134,
            -2366.8932130882413,
            124918.62621430142
        ]
    },
    "fit_metrics": {
        "model_type": "poly2",
        "n_points_valid": 13,
        "rmse_px": 94.35310293230712,
        "mae_px": 83.2813863753226,
        "p95_px": 163.93969069949733
    }
}